qai/agent/__init__.py
qai/agent/agents/campaign_agent.py
qai/agent/agents/conversation_agent.py
qai/agent/agents/email_agent.py
qai/agent/agents/find_agent.py
qai/agent/agents/google/google_places_agent.py
qai/agent/agents/sqlquery_agent.py
qai/agent/agents/tools/__init__.py
qai/agent/agents/tools/outreach.py
qai/agent/agents/worker/__init__.py
qai/agent/basic.py
qai/agent/data/__init__.py
qai/agent/data/state_codes.py
qai/agent/db/__init__.py
qai/agent/db/existing_customers_db.py
qai/agent/db/lead_db.py
qai/agent/llama_index/llm_program.py
qai/agent/models/__init__.py
qai/agent/models/lead_model.py
qai/agent/sessions/__init__.py
qai/agent/sessions/qai_session.py
qai/agent/tools/__init__.py
qai/agent/tools/google/google_places.py
qai/agent/tools/types.py
qai/agent/utils/__init__.py
qai/agent/utils/db_utils.py
qai/agent/utils/distribute.py
qai/agent/utils/schema_utils.py
qai/agent/utils/utils.py
qai_agent-0.6.1.dist-info/METADATA
qai_agent-0.6.1.dist-info/WHEEL
qai_agent-0.6.1.dist-info/RECORD
