Metadata-Version: 2.1
Name: qai-agent
Version: 0.6.1
Summary: Qai Agents for the Qai AI Platform
Author: parnell
Author-email: 152523161+leeparnell@users.noreply.github.com
Requires-Python: >=3.11,<3.12
Classifier: Programming Language :: Python :: 3
Classifier: Programming Language :: Python :: 3.11
Requires-Dist: instructor (>=1.3.2,<2.0.0)
Requires-Dist: llama-index-agent-openai (>=0.2.5,<0.3.0)
Requires-Dist: llama-index-core (>=0.10.37,<0.11.0)
Requires-Dist: llama-index-embeddings-huggingface (>=0.2.0,<0.3.0)
Requires-Dist: llama-index-embeddings-openai (>=0.1.7,<0.2.0)
Requires-Dist: llama-index-llms-openai (>=0.1.19,<0.2.0)
Requires-Dist: llama-index-llms-replicate (>=0.1.3,<0.2.0)
Requires-Dist: llama-index-program-openai (>=0.1.5)
Requires-Dist: llama-index-tools-database (>=0.1.3,<0.2.0)
Requires-Dist: llama-index-tools-google (>=0.1.3,<0.2.0)
Requires-Dist: llama-index-vector-stores-mongodb (>=0.1.4,<0.2.0)
Requires-Dist: multiprocess (>=0.70.16,<0.71.0)
Requires-Dist: mysql-connector-python (>=8.4.0,<9.0.0)
Requires-Dist: openai (>=1.23.2,<2.0.0)
Requires-Dist: pandas (>=2.2.1,<3.0.0)
Requires-Dist: pdl-api (>=0.1.2,<0.2.0)
Requires-Dist: pi-blink (>=1.0.3,<2.0.0)
Requires-Dist: pi-conf (>=0.8.5,<0.9.0)
Requires-Dist: pi-log (>=0.5.8.1,<0.6.0.0)
Requires-Dist: pip (>=24.0,<25.0)
Requires-Dist: pydantic (>=2.7.0,<3.0.0)
Requires-Dist: pymongo (>=4.6.3,<5.0.0)
Requires-Dist: python-dateutil (==2.8.2)
Requires-Dist: python-dotenv (>=1.0.1,<2.0.0)
Requires-Dist: qai-ai (>=0.6.0,<0.7.0)
Requires-Dist: qai-core (>=0.6.0,<0.7.0)
Requires-Dist: qai-schema (>=0.6.2.1,<0.7.0.0)
Requires-Dist: sqlalchemy (>=2.0.29,<3.0.0)
